auth_lib/__init__.py
auth_lib/models.py
auth_lib/services.py
auth_lib_sp-0.1.0.dist-info/LICENSE
auth_lib_sp-0.1.0.dist-info/METADATA
auth_lib_sp-0.1.0.dist-info/WHEEL
auth_lib_sp-0.1.0.dist-info/top_level.txt
auth_lib_sp-0.1.0.dist-info/RECORD
