Metadata-Version: 2.1
Name: auth-lib-sp
Version: 0.1.0
Summary: Library for token verification
Author: Sachikia
License: MIT
License-File: LICENSE
Requires-Dist: requests (==2.28.1)
Requires-Dist: djangorestframework (==3.14.0)
Requires-Dist: djangorestframework-simplejwt (==5.2.1)
Requires-Dist: django-pymemcache (==1.0.0)
